{
  "type": "FeatureCollection",
  "features": [
    {
      "type": "Feature",
      "geometry": {
        "type": "Point",
        "coordinates": [
          11.41639,
          44.47222
        ]
      },
      "properties": {
        "station_id": "2c301b04-5cc0-505b-86e8-97c7ffd4d77f",
        "ground_truth_value": 15.5,
        "pollutant": "PM10",
        "period_key": "2024-04",
        "predicted_value": 16.55150604248047
      }
    },
    {
      "type": "Feature",
      "geometry": {
        "type": "Point",
        "coordinates": [
          11.32833,
          44.49972
        ]
      },
      "properties": {
        "station_id": "baa4dffa-1580-514c-9a77-03b3676652c4",
        "ground_truth_value": 17.0,
        "pollutant": "PM10",
        "period_key": "2024-04",
        "predicted_value": 17.191469192504883
      }
    },
    {
      "type": "Feature",
      "geometry": {
        "type": "Point",
        "coordinates": [
          11.28611,
          44.5
        ]
      },
      "properties": {
        "station_id": "f572499b-6dde-5854-aecb-c3d279cb2189",
        "ground_truth_value": 14.0,
        "pollutant": "PM10",
        "period_key": "2024-04",
        "predicted_value": 18.813264846801758
      }
    }
  ]
}