{
  "type": "FeatureCollection",
  "features": [
    {
      "type": "Feature",
      "geometry": {
        "type": "Point",
        "coordinates": [
          9.3275,
          45.48278
        ]
      },
      "properties": {
        "station_id": "1696157f-edc1-575f-90fa-fc0444d61362",
        "ground_truth_value": 6.187472083333333,
        "pollutant": "O3",
        "period_key": "2024-11",
        "predicted_value": null
      }
    },
    {
      "type": "Feature",
      "geometry": {
        "type": "Point",
        "coordinates": [
          9.16698,
          45.5476
        ]
      },
      "properties": {
        "station_id": "1b00760d-d62b-5edf-bbeb-8147e75df16c",
        "ground_truth_value": 8.231538333333335,
        "pollutant": "O3",
        "period_key": "2024-11",
        "predicted_value": 18.184289932250977
      }
    },
    {
      "type": "Feature",
      "geometry": {
        "type": "Point",
        "coordinates": [
          9.23583,
          45.47833
        ]
      },
      "properties": {
        "station_id": "720d2dcf-a89f-56e4-9f17-28e9669b7bea",
        "ground_truth_value": 6.6602910416666665,
        "pollutant": "O3",
        "period_key": "2024-11",
        "predicted_value": 25.775463104248047
      }
    }
  ]
}